ptpimg_uploader.py
ptpimg_uploader-0.13.dist-info/licenses/LICENSE
ptpimg_uploader-0.13.dist-info/METADATA
ptpimg_uploader-0.13.dist-info/WHEEL
ptpimg_uploader-0.13.dist-info/entry_points.txt
ptpimg_uploader-0.13.dist-info/top_level.txt
ptpimg_uploader-0.13.dist-info/RECORD
