Metadata-Version: 2.4
Name: ptpimg_uploader
Version: 0.13
Summary: PTPImg uploader, handles local files and URLs, from the commandline
Home-page: https://github.com/theirix/ptpimg-uploader
Author: theirix
Author-email: theirix@gmail.com
License: BSD
Keywords: image uploader
Classifier: Development Status :: 4 - Beta
Classifier: Topic :: Utilities
Requires-Python: >=3.3
License-File: LICENSE
Requires-Dist: requests
Provides-Extra: dev
Requires-Dist: requests-mock; extra == "dev"
Requires-Dist: black; extra == "dev"
Dynamic: author
Dynamic: author-email
Dynamic: classifier
Dynamic: description
Dynamic: description-content-type
Dynamic: home-page
Dynamic: keywords
Dynamic: license
Dynamic: license-file
Dynamic: provides-extra
Dynamic: requires-dist
Dynamic: requires-python
Dynamic: summary
